wfpt.cpython-310-darwin.so
cdfdif_wrapper.cpython-310-darwin.so
hddm_wfpt-0.1.6.dist-info/RECORD
hddm_wfpt-0.1.6.dist-info/WHEEL
hddm_wfpt-0.1.6.dist-info/top_level.txt
hddm_wfpt-0.1.6.dist-info/METADATA
hddm_wfpt-0.1.6.dist-info/licenses/LICENSE
hddm_wfpt/cdfdif_wrapper.pyx
hddm_wfpt/__init__.py
hddm_wfpt/cdfdif.c
hddm_wfpt/pdf.pxi
hddm_wfpt/wfpt.pyx
hddm_wfpt/integrate.pxi
hddm_wfpt/cdfdif.h
