Metadata-Version: 2.4
Name: hddm_wfpt
Version: 0.1.6
Summary: HDDM is a python module that implements Hierarchical Bayesian estimation of Drift Diffusion Models.
Author-email: Alexander Fengler <alexander_fengler@brown.edu>, Paul Xu <yang_xu@brown.edu>, Michael Frank <michael_frank@brown.edu>
Project-URL: Homepage, https://github.com/lnccbrown/hddm-wfpt
Project-URL: Bug Tracker, https://github.com/lnccbrown/hddm-wfpt/issues
Classifier: Development Status :: 5 - Production/Stable
Classifier: Environment :: Console
Classifier: Operating System :: OS Independent
Classifier: Intended Audience :: Science/Research
Classifier: License :: OSI Approved :: BSD License
Classifier: Programming Language :: Python
Classifier: Topic :: Scientific/Engineering
Requires-Python: <3.15,>=3.10
License-File: LICENSE
Requires-Dist: numpy>=2.0
Requires-Dist: scipy>=1.15.2
Dynamic: license-file
